{"commitInfo":{"timestamp":1763295312305,"operation":"WRITE","operationParameters":{"mode":"Append","partitionBy":"[]"},"readVersion":5,"isolationLevel":"Serializable","isBlindAppend":true,"operationMetrics":{"numFiles":"2","numOutputRows":"2","numOutputBytes":"2399"},"engineInfo":"Apache-Spark/3.4.1 Delta-Lake/2.4.0","txnId":"8481fd15-bb24-4194-a231-080a28285dfd"}}
{"add":{"path":"part-00000-5749b0fd-81cb-42ed-a1f7-c80396767629-c000.snappy.parquet","partitionValues":{},"size":1224,"modificationTime":1763295312299,"dataChange":true,"stats":"{\"numRecords\":1,\"minValues\":{\"id\":8,\"name\":\"Henry\",\"department\":\"Engineering\",\"salary\":98000},\"maxValues\":{\"id\":8,\"name\":\"Henry\",\"department\":\"Engineering\",\"salary\":98000},\"nullCount\":{\"id\":0,\"name\":0,\"department\":0,\"salary\":0},\"tightBounds\":true}"}}
{"add":{"path":"part-00001-20a63484-90ce-4819-8fe1-268c9d453770-c000.snappy.parquet","partitionValues":{},"size":1175,"modificationTime":1763295312302,"dataChange":true,"stats":"{\"numRecords\":1,\"minValues\":{\"id\":9,\"name\":\"Iris\",\"department\":\"Sales\",\"salary\":82000},\"maxValues\":{\"id\":9,\"name\":\"Iris\",\"department\":\"Sales\",\"salary\":82000},\"nullCount\":{\"id\":0,\"name\":0,\"department\":0,\"salary\":0},\"tightBounds\":true}"}}
