{"commitInfo":{"timestamp":1700000200000,"operation":"DELETE","operationParameters":{"predicate":"[\"(category = 'A')\"]"},"readVersion":1,"isolationLevel":"Serializable","isBlindAppend":false,"operationMetrics":{"numRemovedFiles":"0","numRemovedBytes":"0","numAddedFiles":"0","numDeletionVectorsAdded":"2","numDeletionVectorsRemoved":"0","numAddedChangeFiles":"0","executionTimeMs":"1250","numDeletedRows":"150","scanTimeMs":"450","rewriteTimeMs":"0"},"engineInfo":"Apache-Spark/3.4.1 Delta-Lake/2.4.0","txnId":"c3d4e5f6-a7b8-9012-cdef-234567890123"}}
{"remove":{"path":"part-00000-a1b2c3d4-e5f6-7890-abcd-111111111111.c000.snappy.parquet","deletionTimestamp":1700000200000,"dataChange":true,"extendedFileMetadata":true,"partitionValues":{},"size":15000}}
{"add":{"path":"part-00000-a1b2c3d4-e5f6-7890-abcd-111111111111.c000.snappy.parquet","partitionValues":{},"size":15000,"modificationTime":1700000100000,"dataChange":true,"stats":"{\"numRecords\":350,\"minValues\":{\"id\":1,\"name\":\"Alice\",\"category\":\"A\",\"value\":10.5},\"maxValues\":{\"id\":350,\"name\":\"Zoe\",\"category\":\"C\",\"value\":999.9},\"nullCount\":{\"id\":0,\"name\":0,\"category\":0,\"value\":0}}","deletionVector":{"storageType":"u","pathOrInlineDv":"vw@~5&4S8{+Jm!pP-Ad","offset":1,"sizeInBytes":45,"cardinality":75}}}
{"remove":{"path":"part-00001-b2c3d4e5-f6a7-8901-bcde-222222222222.c000.snappy.parquet","deletionTimestamp":1700000200000,"dataChange":true,"extendedFileMetadata":true,"partitionValues":{},"size":15000}}
{"add":{"path":"part-00001-b2c3d4e5-f6a7-8901-bcde-222222222222.c000.snappy.parquet","partitionValues":{},"size":15000,"modificationTime":1700000100000,"dataChange":true,"stats":"{\"numRecords\":350,\"minValues\":{\"id\":351,\"name\":\"Aaron\",\"category\":\"A\",\"value\":11.2},\"maxValues\":{\"id\":700,\"name\":\"Zara\",\"category\":\"C\",\"value\":998.8},\"nullCount\":{\"id\":0,\"name\":0,\"category\":0,\"value\":0}}","deletionVector":{"storageType":"u","pathOrInlineDv":"vw@~5&4S8{+Jm!pP-Ad","offset":46,"sizeInBytes":40,"cardinality":75}}}

